hashub_docapp/__init__.py
hashub_docapp/batch.py
hashub_docapp/cli.py
hashub_docapp/client.py
hashub_docapp/enhancement.py
hashub_docapp/exceptions.py
hashub_docapp/languages.py
hashub_docapp/models.py
hashub_docapp/progress.py
hashub_docapp/utils.py
hashub_docapp-1.0.0.dist-info/licenses/LICENSE
hashub_docapp-1.0.0.dist-info/METADATA
hashub_docapp-1.0.0.dist-info/WHEEL
hashub_docapp-1.0.0.dist-info/entry_points.txt
hashub_docapp-1.0.0.dist-info/top_level.txt
hashub_docapp-1.0.0.dist-info/RECORD
