Metadata-Version: 2.4
Name: hashub-docapp
Version: 1.0.0
Summary: Professional Python SDK for the HashubDocApp API - Advanced OCR, document conversion, and text extraction service
Home-page: https://github.com/hasanbahadir/hashub-doc-sdk
Author: Hashub Team
Author-email: Hashub Team <support@hashub.dev>
Maintainer-email: Hashub Team <support@hashub.dev>
License: MIT
Project-URL: Homepage, https://github.com/hasanbahadir/hashub-doc-sdk
Project-URL: Documentation, https://doc.hashub.dev
Project-URL: Repository, https://github.com/hasanbahadir/hashub-doc-sdk
Project-URL: Bug Reports, https://github.com/hasanbahadir/hashub-doc-sdk/issues
Project-URL: API Reference, https://doc.hashub.dev/api
Keywords: ocr,pdf,document,conversion,text-extraction,image-processing,api-client,hashub,batch-processing
Classifier: Development Status :: 5 - Production/Stable
Classifier: Intended Audience :: Developers
Classifier: Topic :: Software Development :: Libraries :: Python Modules
Classifier: Topic :: Text Processing
Classifier: Topic :: Scientific/Engineering :: Image Recognition
Classifier: License :: OSI Approved :: MIT License
Classifier: Programming Language :: Python :: 3
Classifier: Programming Language :: Python :: 3.8
Classifier: Programming Language :: Python :: 3.9
Classifier: Programming Language :: Python :: 3.10
Classifier: Programming Language :: Python :: 3.11
Classifier: Programming Language :: Python :: 3.12
Classifier: Operating System :: OS Independent
Requires-Python: >=3.8
License-File: LICENSE
Requires-Dist: requests>=2.25.0
Requires-Dist: urllib3>=1.26.0
Requires-Dist: typing-extensions>=3.7.4; python_version < "3.8"
Dynamic: author
Dynamic: home-page
Dynamic: license-file
Dynamic: requires-python
